[
  {
    "id": 2,
    "name": "瑞穂",
    "url": "https://coderdojo-mizuho.connpass.com/",
    "event_id": 6723,
    "event_title": "No.126 CoderDojo瑞穂 / コメダ珈琲本店",
    "event_date": "2024-05-12T17:00:00.000+09:00",
    "event_end_at": "2024-05-12T19:00:00.000+09:00",
    "event_url": "https://coderdojo-mizuho.connpass.com/event/313293/",
    "prefecture": "愛知",
    "participants": 11,
    "event_update_at": "2024-03-13T09:42:06.000+09:00",
    "address": "愛知県名古屋市瑞穂区上山町3ー14ー8",
    "place": "コメダ本店",
    "limit": 12
  },
  {
    "id": 9,
    "name": "さいたま",
    "url": "http://coderdojo-saitama.com/",
    "event_id": 6924,
    "event_title": "第90回CoderDojoさいたま",
    "event_date": "2024-05-19T14:00:00.000+09:00",
    "event_end_at": "2024-05-19T16:00:00.000+09:00",
    "event_url": "https://coderdojo-saitama.connpass.com/event/316984/",
    "prefecture": "埼玉",
    "participants": 0,
    "event_update_at": "2024-04-27T11:23:04.000+09:00",
    "address": "埼玉県さいたま市大宮区宮町1-5 銀座ビル6階",
    "place": "貸会議室６F",
    "limit": 16
  },
  {
    "id": 13,
    "name": "こだいら",
    "url": "https://coderdojo-kodaira.github.io/",
    "event_id": 6814,
    "event_title": "第327回 オンライン（Discord）",
    "event_date": "2024-05-08T19:00:00.000+09:00",
    "event_end_at": "2024-05-08T21:00:00.000+09:00",
    "event_url": "https://coderdojo-jp-kodaira.connpass.com/event/315351/",
    "prefecture": "東京",
    "participants": 0,
    "event_update_at": "2024-04-03T16:41:25.000+09:00",
    "address": "",
    "place": "オンライン（Discord）",
    "limit": null
  },
  {
    "id": 18,
    "name": "調布",
    "url": "https://coderdojochofu.hatenablog.jp/",
    "event_id": 6839,
    "event_title": "第89回 CoderDojo 調布 (募集開始前 少々お待ちください)",
    "event_date": "2024-05-26T09:30:00.000+09:00",
    "event_end_at": "2024-05-26T12:30:00.000+09:00",
    "event_url": "https://coderdojo-chofu.doorkeeper.jp/events/171940",
    "prefecture": "東京",
    "participants": 0,
    "event_update_at": "2024-04-11T22:57:38.941+09:00",
    "address": "東京都調布市国領町２丁目５−１５",
    "place": "あくろす会場",
    "limit": 15
  },
  {
    "id": 30,
    "name": "豊橋",
    "url": "https://www.facebook.com/coderdojo.toyohashi/",
    "event_id": 6797,
    "event_title": "CoderDojo豊橋の開校について（2024年4月の開催予定）",
    "event_date": "2024-04-04T16:30:00.000+09:00",
    "event_end_at": "2024-04-30T18:00:00.000+09:00",
    "event_url": "https://coderdojo-toyohashi.doorkeeper.jp/events/171615",
    "prefecture": "愛知",
    "participants": 10,
    "event_update_at": "2024-04-25T09:07:07.405+09:00",
    "address": "〒440-0016 愛知県豊橋市牛川町松下２０−１",
    "place": "豊橋創造大学D22ゼミ室",
    "limit": 12
  },
  {
    "id": 32,
    "name": "天白",
    "url": "https://coderdojo-tempaku.hatenablog.com/",
    "event_id": 6708,
    "event_title": "CoderDojo天白N197",
    "event_date": "2024-05-11T13:30:00.000+09:00",
    "event_end_at": "2024-05-11T16:00:00.000+09:00",
    "event_url": "https://tempaku.connpass.com/event/312236/",
    "prefecture": "愛知",
    "participants": 2,
    "event_update_at": "2024-03-04T10:51:44.000+09:00",
    "address": "〒468-0027 愛知県名古屋市天白区天白町島田黒石4050",
    "place": "天白区生涯学習センター IT室",
    "limit": 8
  },
  {
    "id": 34,
    "name": "長岡京",
    "url": "https://coderdojo-nagaokakyo.doorkeeper.jp/",
    "event_id": 6881,
    "event_title": "CoderDojo長岡京〜学生のためのプログラミング道場〜 95回目",
    "event_date": "2024-05-19T13:30:00.000+09:00",
    "event_end_at": "2024-05-19T16:00:00.000+09:00",
    "event_url": "https://coderdojo-nagaokakyo.doorkeeper.jp/events/172198",
    "prefecture": "京都",
    "participants": 4,
    "event_update_at": "2024-04-21T23:15:20.107+09:00",
    "address": "〒617-0826 京都府長岡京市開田４丁目２−９ ヘルプビル3F",
    "place": "長岡京コワーキングスペース",
    "limit": 8
  },
  {
    "id": 35,
    "name": "奈良",
    "url": "https://coderdojo-nara.github.io/",
    "event_id": 6882,
    "event_title": "【平群町開催】：子どもと大人のプログラミングクラブ（No.17）",
    "event_date": "2024-05-11T09:00:00.000+09:00",
    "event_end_at": "2024-05-11T12:00:00.000+09:00",
    "event_url": "https://coderdojo-nara-ikoma.connpass.com/event/316450/",
    "prefecture": "奈良",
    "participants": 0,
    "event_update_at": "2024-04-15T12:59:41.000+09:00",
    "address": "奈良県生駒郡平群町西宮1-10-5",
    "place": "西宮公民館",
    "limit": 30
  },
  {
    "id": 42,
    "name": "西宮・梅田",
    "url": "https://coderdojo-nishinomiya.info/",
    "event_id": 6756,
    "event_title": "子ども向けプログラミング道場：コーダー道場150回目@梅田",
    "event_date": "2024-05-18T14:00:00.000+09:00",
    "event_end_at": "2024-05-18T18:00:00.000+09:00",
    "event_url": "https://coderdojo-nishinomiya.doorkeeper.jp/events/169906",
    "prefecture": "大阪",
    "participants": 5,
    "event_update_at": "2024-04-27T20:11:22.153+09:00",
    "address": "大阪府大阪市北区大深江町3-1 グランフロント大阪 タワーC 16階",
    "place": "gusuku Ashibinaa OSAKA（アールスリーインスティテュート）",
    "limit": 0
  },
  {
    "id": 44,
    "name": "大阪狭山",
    "url": "https://coderdojo-osakasayama.doorkeeper.jp/",
    "event_id": 6910,
    "event_title": "子ども向けプログラミング道場：コーダー道場 75回目@大阪狭山",
    "event_date": "2024-05-19T09:30:00.000+09:00",
    "event_end_at": "2024-05-19T12:00:00.000+09:00",
    "event_url": "https://coderdojo-osakasayama.doorkeeper.jp/events/172614",
    "prefecture": "大阪",
    "participants": 3,
    "event_update_at": "2024-04-24T15:55:20.683+09:00",
    "address": "大阪狭山市狭山四丁目2303番地の2  (2階)",
    "place": "UPっぷ（子育て支援・世代間交流センター）",
    "limit": 3
  },
  {
    "id": 52,
    "name": "紙屋町",
    "url": "https://www.facebook.com/coderdojo.kamiyacho/",
    "event_id": 6909,
    "event_title": "【5/11(土) 会場：ポートインク】CoderDojo紙屋町 91回目",
    "event_date": "2024-05-11T13:45:00.000+09:00",
    "event_end_at": "2024-05-11T16:30:00.000+09:00",
    "event_url": "https://coderdojo-hiroshima.doorkeeper.jp/events/172602",
    "prefecture": "広島",
    "participants": 3,
    "event_update_at": "2024-04-24T18:28:02.021+09:00",
    "address": "広島市中区本川町3丁目1番5号 シーアイマンション2F",
    "place": "ポートインク",
    "limit": 15
  },
  {
    "id": 54,
    "name": "久留米",
    "url": "https://www.facebook.com/CoderDojoKurume/",
    "event_id": 6891,
    "event_title": "【会場開催】第92回CoderDojo久留米",
    "event_date": "2024-05-25T14:00:00.000+09:00",
    "event_end_at": "2024-05-25T16:30:00.000+09:00",
    "event_url": "https://coderdojo-kurume.connpass.com/event/316575/",
    "prefecture": "福岡",
    "participants": 7,
    "event_update_at": "2024-04-20T16:49:07.000+09:00",
    "address": "福岡県久留米市中央町11-1(第一田中ビル2階)",
    "place": "Mekuruto",
    "limit": null
  },
  {
    "id": 66,
    "name": "高槻",
    "url": "https://www.facebook.com/coderdojotakatsuki/",
    "event_id": 6826,
    "event_title": "CoderDojo高槻 第65回",
    "event_date": "2024-06-02T13:15:00.000+09:00",
    "event_end_at": "2024-06-02T16:00:00.000+09:00",
    "event_url": "https://coderdojo-takatsuki.connpass.com/event/315740/",
    "prefecture": "大阪",
    "participants": 1,
    "event_update_at": "2024-04-07T18:18:16.000+09:00",
    "address": "高槻市紺屋町1番2号",
    "place": "クロスパル高槻 302会議室",
    "limit": 10
  },
  {
    "id": 71,
    "name": "尾張",
    "url": "https://coderdojoowari.org/",
    "event_id": 6713,
    "event_title": "第86回 CoderDojo Owari",
    "event_date": "2024-05-12T10:00:00.000+09:00",
    "event_end_at": "2024-05-12T12:00:00.000+09:00",
    "event_url": "https://coderdojoowari.connpass.com/event/309550/",
    "prefecture": "愛知",
    "participants": 8,
    "event_update_at": "2024-04-10T20:05:30.000+09:00",
    "address": "愛知県岩倉市本町神明西２０",
    "place": "岩倉市生涯学習センター",
    "limit": null
  },
  {
    "id": 72,
    "name": "富田林",
    "url": "https://coderdojotondabayashi.github.io/main/",
    "event_id": 6877,
    "event_title": "CoderDojo富田林 第38回：子ども向けプログラミングクラブ",
    "event_date": "2024-05-11T15:30:00.000+09:00",
    "event_end_at": "2024-05-11T17:30:00.000+09:00",
    "event_url": "https://coderdojotondabayashi.connpass.com/event/316383/",
    "prefecture": "大阪",
    "participants": 0,
    "event_update_at": "2024-04-14T16:36:50.000+09:00",
    "address": "富田林市寺池台一丁目９番７０号S3号棟",
    "place": "金剛地区魅力向上拠点『∞KON　ROOM』",
    "limit": 5
  },
  {
    "id": 73,
    "name": "ひたちなか",
    "url": "https://www.facebook.com/coderdojo.hitachinaka/",
    "event_id": 6905,
    "event_title": "第74回 CoderDojo Hitachinaka",
    "event_date": "2024-05-06T13:30:00.000+09:00",
    "event_end_at": "2024-05-06T15:30:00.000+09:00",
    "event_url": "https://coderdojo-hitachinaka.connpass.com/event/317106/",
    "prefecture": "茨城",
    "participants": 0,
    "event_update_at": "2024-04-28T01:01:09.000+09:00",
    "address": "ひたちなか市石川町11-1",
    "place": "ふぁみりこらぼ",
    "limit": 9
  },
  {
    "id": 79,
    "name": "会津",
    "url": "https://coderdojoaizu.mystrikingly.com/",
    "event_id": 6873,
    "event_title": "第６回 CoderDojo BANDAI",
    "event_date": "2024-05-11T13:30:00.000+09:00",
    "event_end_at": "2024-05-11T15:45:00.000+09:00",
    "event_url": "https://coderdojo-aizu.doorkeeper.jp/events/172133",
    "prefecture": "福島",
    "participants": 2,
    "event_update_at": "2024-04-16T07:19:28.019+09:00",
    "address": "福島県耶麻郡磐梯町大字磐梯山道３１１番地６２ 磐梯町交流館",
    "place": "磐梯町交流館",
    "limit": 10
  },
  {
    "id": 89,
    "name": "さくら",
    "url": "https://coderdojo-sakura.github.io/",
    "event_id": 6766,
    "event_title": "第６６回CoderDojo さくら",
    "event_date": "2024-05-19T10:00:00.000+09:00",
    "event_end_at": "2024-05-19T12:00:00.000+09:00",
    "event_url": "https://coderdojosakura.connpass.com/event/313928/",
    "prefecture": "栃木",
    "participants": 0,
    "event_update_at": "2024-03-21T10:13:24.000+09:00",
    "address": "〒329-2151 栃木県矢板市幸岡１４９８−１",
    "place": "HCCソフト（株）研究開発センター（旧矢板西小学校）",
    "limit": 10
  },
  {
    "id": 102,
    "name": "福岡",
    "url": "https://www.facebook.com/CoderDojoFukuoka/",
    "event_id": 6893,
    "event_title": "第80回 CoderDojo 福岡 【オンライン】+ 会場：fgn ２階（大名小跡地）",
    "event_date": "2024-05-11T14:00:00.000+09:00",
    "event_end_at": "2024-05-11T16:00:00.000+09:00",
    "event_url": "https://coderdojo-fukuoka.connpass.com/event/316840/",
    "prefecture": "福岡",
    "participants": 10,
    "event_update_at": "2024-04-19T08:09:22.000+09:00",
    "address": "福岡県福岡市中央区大名2-6-11",
    "place": "オンライン + Fukuoka Growth Next",
    "limit": 20
  },
  {
    "id": 117,
    "name": "立川",
    "url": "https://coderdojotachikawa.github.io/",
    "event_id": 6838,
    "event_title": "第50回 子どものためのプログラミング道場 - CoderDojo 立川",
    "event_date": "2024-05-18T09:30:00.000+09:00",
    "event_end_at": "2024-05-18T11:30:00.000+09:00",
    "event_url": "https://coderdojo-tachikawa.connpass.com/event/304933/",
    "prefecture": "東京",
    "participants": 3,
    "event_update_at": "2024-04-10T09:31:52.000+09:00",
    "address": "立川市錦町3丁目2番26号",
    "place": "子ども未来センター",
    "limit": 16
  },
  {
    "id": 129,
    "name": "三島・沼津",
    "url": "https://coderdojo-mn.com/",
    "event_id": 6878,
    "event_title": "第33回 CoderDojo 三島/沼津",
    "event_date": "2024-05-12T10:00:00.000+09:00",
    "event_end_at": "2024-05-12T12:00:00.000+09:00",
    "event_url": "https://coderdojo-mn.connpass.com/event/316324/",
    "prefecture": "静岡",
    "participants": 2,
    "event_update_at": "2024-04-14T08:01:35.000+09:00",
    "address": "沼津市大岡4044-24",
    "place": "静岡県立工科短期大学校 沼津キャンパス（旧:沼津テクノカレッジ）",
    "limit": 10
  },
  {
    "id": 136,
    "name": "香椎",
    "url": "https://coderdojo-kashii.connpass.com/",
    "event_id": 6925,
    "event_title": "第58回CoderDojo香椎",
    "event_date": "2024-05-12T09:30:00.000+09:00",
    "event_end_at": "2024-05-12T12:00:00.000+09:00",
    "event_url": "https://coderdojo-kashii.connpass.com/event/316699/",
    "prefecture": "福岡",
    "participants": 5,
    "event_update_at": "2024-04-27T10:01:52.000+09:00",
    "address": "福岡市東区千早4丁目21番45号",
    "place": "なみきスクエア　和室",
    "limit": 10
  },
  {
    "id": 140,
    "name": "厚木",
    "url": "https://coderdojo-atsugi.connpass.com/",
    "event_id": 6801,
    "event_title": "第45回 CoderDojo厚木",
    "event_date": "2024-05-19T10:30:00.000+09:00",
    "event_end_at": "2024-05-19T12:30:00.000+09:00",
    "event_url": "https://coderdojo-atsugi.connpass.com/event/314797/",
    "prefecture": "神奈川",
    "participants": 0,
    "event_update_at": "2024-04-27T06:15:58.000+09:00",
    "address": "神奈川県厚木市中町2丁目12-15",
    "place": "アミューあつぎ 6F",
    "limit": 6
  },
  {
    "id": 145,
    "name": "日進",
    "url": "https://coderdojo-nisshin.connpass.com/",
    "event_id": 6900,
    "event_title": "CoderDojo日進 子供向けプログラミング道場(会場&オンライン)2023/05/11",
    "event_date": "2024-05-11T09:00:00.000+09:00",
    "event_end_at": "2024-05-11T11:00:00.000+09:00",
    "event_url": "https://coderdojo-nisshin.connpass.com/event/317049/",
    "prefecture": "愛知",
    "participants": 1,
    "event_update_at": "2024-04-21T11:33:20.000+09:00",
    "address": "愛知県日進市蟹甲町中島277-1",
    "place": "にぎわい交流館",
    "limit": null
  },
  {
    "id": 149,
    "name": "白河",
    "url": "https://coderdojoshirakawa.hateblo.jp/entry/top",
    "event_id": 6888,
    "event_title": "第61回 CoderDojo白河",
    "event_date": "2024-05-11T09:30:00.000+09:00",
    "event_end_at": "2024-05-11T11:30:00.000+09:00",
    "event_url": "https://coderdojo-shirakawa.doorkeeper.jp/events/172289",
    "prefecture": "福島",
    "participants": 1,
    "event_update_at": "2024-04-17T20:52:50.810+09:00",
    "address": "〒961-0905 福島県白河市本町２",
    "place": "マイタウン白河 2F 中会議室1",
    "limit": 11
  },
  {
    "id": 156,
    "name": "古河",
    "url": "https://coderdojokoga.connpass.com/",
    "event_id": 6778,
    "event_title": "第78回CoderDojo Koga（コーダー道場 古河）",
    "event_date": "2024-05-25T10:00:00.000+09:00",
    "event_end_at": "2024-05-25T12:00:00.000+09:00",
    "event_url": "https://coderdojokoga.connpass.com/event/314013/",
    "prefecture": "茨城",
    "participants": 4,
    "event_update_at": "2024-03-20T14:29:52.000+09:00",
    "address": "茨城県古河市鴻巣７５８",
    "place": "三桜工業株式会社　古河事業所",
    "limit": 16
  },
  {
    "id": 165,
    "name": "喜多方",
    "url": "https://www.coderdojo-kitakata.com/",
    "event_id": 6926,
    "event_title": "第59回 CoderDojo喜多方 in 喜多方プラザ",
    "event_date": "2024-05-11T10:00:00.000+09:00",
    "event_end_at": "2024-05-11T12:00:00.000+09:00",
    "event_url": "https://coderdojo-kitakata.doorkeeper.jp/events/172824",
    "prefecture": "福島",
    "participants": 0,
    "event_update_at": "2024-04-27T15:10:02.168+09:00",
    "address": "福島県喜多方市字押切二丁目1番地",
    "place": "喜多方プラザ文化センター 2F 第二会議室",
    "limit": 15
  },
  {
    "id": 182,
    "name": "瀬戸",
    "url": "https://coderdojo-seto.jp/",
    "event_id": 6805,
    "event_title": "【無料】【見学OK】CoderDojo瀬戸(第123回) 子供プログラミングコミュニティ",
    "event_date": "2024-05-19T10:00:00.000+09:00",
    "event_end_at": "2024-05-19T12:30:00.000+09:00",
    "event_url": "https://coderdojo-seto.connpass.com/event/315037/",
    "prefecture": "愛知",
    "participants": 17,
    "event_update_at": "2024-04-01T12:23:56.000+09:00",
    "address": "瀬戸市道泉町53番地の5",
    "place": "ぐるっぺ道泉",
    "limit": null
  },
  {
    "id": 184,
    "name": "あざみ野",
    "url": "https://coderdojo-azamino.connpass.com/",
    "event_id": 6887,
    "event_title": "第67回CoderDojoあざみ野",
    "event_date": "2024-05-25T14:00:00.000+09:00",
    "event_end_at": "2024-05-25T16:00:00.000+09:00",
    "event_url": "https://coderdojo-azamino.connpass.com/event/316692/",
    "prefecture": "神奈川",
    "participants": 0,
    "event_update_at": "2024-04-17T21:38:30.000+09:00",
    "address": "横浜市青葉区あざみ野南1-17-3",
    "place": "アートフォーラムあざみ野 2F セミナールーム2",
    "limit": 7
  },
  {
    "id": 186,
    "name": "名護",
    "url": "https://coderdojo-nago.connpass.com/",
    "event_id": 6834,
    "event_title": "CoderDojo名護（あけみおSKYドーム・会議室）",
    "event_date": "2024-05-18T14:30:00.000+09:00",
    "event_end_at": "2024-05-18T16:00:00.000+09:00",
    "event_url": "https://coderdojo-nago.connpass.com/event/315984/",
    "prefecture": "沖縄",
    "participants": 8,
    "event_update_at": "2024-04-20T20:02:46.000+09:00",
    "address": "沖縄県名護市宮里４９２",
    "place": "あけみおSKYドーム・会議室",
    "limit": null
  },
  {
    "id": 189,
    "name": "まちだ",
    "url": "https://coderdojo-machida.connpass.com/",
    "event_id": 6897,
    "event_title": "CoderDojoまちだ　第５８回",
    "event_date": "2024-05-26T13:30:00.000+09:00",
    "event_end_at": "2024-05-26T16:30:00.000+09:00",
    "event_url": "https://coderdojo-machida.connpass.com/event/317087/",
    "prefecture": "東京",
    "participants": 2,
    "event_update_at": "2024-04-21T21:01:26.000+09:00",
    "address": "東京都町田市原町田４丁目９−８ サウスフロントタワー町田内",
    "place": "町田市民フォーラム",
    "limit": null
  },
  {
    "id": 190,
    "name": "溝口",
    "url": "https://coderdojo-mizonokuchi.connpass.com/",
    "event_id": 6792,
    "event_title": "5/12無料の子どもプログラミングサークル【第53回CoderDojo溝口】(川崎市,初心者歓迎)",
    "event_date": "2024-05-12T14:00:00.000+09:00",
    "event_end_at": "2024-05-12T16:00:00.000+09:00",
    "event_url": "https://coderdojo-mizonokuchi.connpass.com/event/314595/",
    "prefecture": "神奈川",
    "participants": 4,
    "event_update_at": "2024-03-27T10:13:09.000+09:00",
    "address": "〒213-0001 川崎市高津区溝口 2-20-1",
    "place": "すくらむ21",
    "limit": 16
  },
  {
    "id": 193,
    "name": "とよなか",
    "url": "https://coderdojo-toyonaka.connpass.com/",
    "event_id": 6755,
    "event_title": "第63回 CoderDojoとよなか（大阪）2024/05/18(土)",
    "event_date": "2024-05-18T09:00:00.000+09:00",
    "event_end_at": "2024-05-18T12:00:00.000+09:00",
    "event_url": "https://coderdojo-toyonaka.connpass.com/event/313626/",
    "prefecture": "大阪",
    "participants": 0,
    "event_update_at": "2024-03-16T00:52:42.000+09:00",
    "address": "豊中市蛍池中町3-2-1-501",
    "place": "豊中市蛍池公民館第１講座室",
    "limit": 22
  },
  {
    "id": 200,
    "name": "岐阜",
    "url": "https://coderdojo-gifu.org/",
    "event_id": 6906,
    "event_title": "第60回 CoderDojo岐阜",
    "event_date": "2024-05-25T09:30:00.000+09:00",
    "event_end_at": "2024-05-25T11:30:00.000+09:00",
    "event_url": "https://coderdojo-gifu.connpass.com/event/317302/",
    "prefecture": "岐阜",
    "participants": 0,
    "event_update_at": "2024-04-23T16:49:34.000+09:00",
    "address": "岐阜県岐阜市司町40番地5",
    "place": "みんなの森 ぎふメディアコスモス「考えるスタジオ」",
    "limit": 18
  },
  {
    "id": 206,
    "name": "吹田",
    "url": "https://coderdojo-suita.doorkeeper.jp/",
    "event_id": 6913,
    "event_title": "子どものためのプログラミング・クラブ：CoderDojo吹田 #36",
    "event_date": "2024-05-25T13:30:00.000+09:00",
    "event_end_at": "2024-05-25T16:00:00.000+09:00",
    "event_url": "https://coderdojo-suita.doorkeeper.jp/events/172606",
    "prefecture": "大阪",
    "participants": 1,
    "event_update_at": "2024-04-24T18:47:17.941+09:00",
    "address": "大阪府吹田市内本町3-19-21",
    "place": "吹一地区公民館（本館）",
    "limit": null
  },
  {
    "id": 218,
    "name": "犬山",
    "url": "https://coderdojo-inuyama.rgr.jp/",
    "event_id": 6919,
    "event_title": "第59回 CoderDojo犬山　（午後）",
    "event_date": "2024-05-19T13:30:00.000+09:00",
    "event_end_at": "2024-05-19T15:30:00.000+09:00",
    "event_url": "https://coderdojo-inuyama.doorkeeper.jp/events/172731",
    "prefecture": "愛知",
    "participants": 0,
    "event_update_at": "2024-04-26T08:36:57.054+09:00",
    "address": "〒484-0081 犬山市大字犬山字中ノ宮43-1",
    "place": "犬山市 丸山地区学習等供用施設",
    "limit": null
  },
  {
    "id": 243,
    "name": "大府",
    "url": "https://coderdojo-obu.connpass.com/",
    "event_id": 6908,
    "event_title": "CoderDojo大府(第80回) 子供向けプログラミング道場 2024/05/05",
    "event_date": "2024-05-05T09:30:00.000+09:00",
    "event_end_at": "2024-05-05T11:30:00.000+09:00",
    "event_url": "https://coderdojo-obu.connpass.com/event/317266/",
    "prefecture": "愛知",
    "participants": 7,
    "event_update_at": "2024-04-23T12:58:00.000+09:00",
    "address": "〒474-0053 愛知県大府市柊山町６丁目１５０−１",
    "place": "おおぶ文化交流の杜 allobu",
    "limit": 14
  },
  {
    "id": 248,
    "name": "矢吹",
    "url": "https://coderdojoyabuki.connpass.com/",
    "event_id": 6894,
    "event_title": "第43回CoderDojo Yabuki",
    "event_date": "2024-05-18T10:00:00.000+09:00",
    "event_end_at": "2024-05-18T12:00:00.000+09:00",
    "event_url": "https://coderdojoyabuki.connpass.com/event/313999/",
    "prefecture": "福島",
    "participants": 0,
    "event_update_at": "2024-04-20T13:04:11.000+09:00",
    "address": "福島県西白河郡矢吹町中町259番地",
    "place": "株式会社コミクリ 東北DXセンター",
    "limit": 12
  },
  {
    "id": 249,
    "name": "加西",
    "url": "https://coderdojokasai.connpass.com/",
    "event_id": 6874,
    "event_title": "第45回 CoderDojo加西",
    "event_date": "2024-05-19T10:15:00.000+09:00",
    "event_end_at": "2024-05-19T12:00:00.000+09:00",
    "event_url": "https://coderdojokasai.connpass.com/event/316320/",
    "prefecture": "兵庫",
    "participants": 0,
    "event_update_at": "2024-04-13T17:58:44.000+09:00",
    "address": "兵庫県加西市北条町北条28-1",
    "place": "加西市立図書館",
    "limit": 6
  },
  {
    "id": 254,
    "name": "青梅",
    "url": "https://coderdojoome.github.io/",
    "event_id": 6917,
    "event_title": "オンライン限定【CoderDojo青梅】第76回",
    "event_date": "2024-05-11T04:30:00.000+09:00",
    "event_end_at": "2024-05-11T16:00:00.000+09:00",
    "event_url": "https://coderdojo-ome.connpass.com/event/317438/",
    "prefecture": "東京",
    "participants": 1,
    "event_update_at": "2024-04-26T22:58:49.000+09:00",
    "address": "オンライン",
    "place": "オンライン",
    "limit": 5
  },
  {
    "id": 260,
    "name": "伊勢原",
    "url": "https://coderdojo-isehara.connpass.com",
    "event_id": 6872,
    "event_title": "第37回　CoderDojo伊勢原",
    "event_date": "2024-05-11T14:00:00.000+09:00",
    "event_end_at": "2024-05-11T16:00:00.000+09:00",
    "event_url": "https://coderdojo-isehara.connpass.com/event/315032/",
    "prefecture": "神奈川",
    "participants": 1,
    "event_update_at": "2024-04-12T07:01:34.000+09:00",
    "address": "伊勢原市田中２９７番地",
    "place": "伊勢原市民活動サポートセンター",
    "limit": 10
  },
  {
    "id": 261,
    "name": "江別",
    "url": "https://coderdojo-ebetsu.connpass.com/",
    "event_id": 6822,
    "event_title": "第３０回 CoderDojo江別",
    "event_date": "2024-05-11T14:00:00.000+09:00",
    "event_end_at": "2024-05-11T16:00:00.000+09:00",
    "event_url": "https://coderdojo-ebetsu.connpass.com/event/315675/",
    "prefecture": "北海道",
    "participants": 2,
    "event_update_at": "2024-04-06T19:59:17.000+09:00",
    "address": "北海道江別市東野幌本町6-43",
    "place": "市民交流施設 ぷらっと",
    "limit": null
  },
  {
    "id": 262,
    "name": "宇治",
    "url": "https://coderdojo-uji.blogspot.com/",
    "event_id": 6883,
    "event_title": "【6/16】第6回 CoderDojo宇治",
    "event_date": "2024-06-16T13:30:00.000+09:00",
    "event_end_at": "2024-06-16T16:00:00.000+09:00",
    "event_url": "https://coderdojo-uji.connpass.com/event/315326/",
    "prefecture": "京都",
    "participants": 1,
    "event_update_at": "2024-04-03T14:34:24.000+09:00",
    "address": "京都府宇治市宇治壱番3",
    "place": "京都文教大学サテライトキャンパス",
    "limit": 4
  },
  {
    "id": 265,
    "name": "八戸@吹上",
    "url": "https://coderdojo-hachinohe.aomori.jp/",
    "event_id": 6885,
    "event_title": "やってみよう！プログラミング ! 第31回 CoderDojo八戸@鮫のゲストハウスDrop in",
    "event_date": "2024-05-12T10:00:00.000+09:00",
    "event_end_at": "2024-05-12T12:00:00.000+09:00",
    "event_url": "https://coderdojo-hachinohe.doorkeeper.jp/events/172233",
    "prefecture": "青森",
    "participants": 2,
    "event_update_at": "2024-04-25T22:58:17.930+09:00",
    "address": "青森県八戸市蟻子5-11",
    "place": "鮫のゲストハウス Drop in",
    "limit": 4
  },
  {
    "id": 270,
    "name": "長門",
    "url": "https://sites.google.com/view/coderdojonagato",
    "event_id": 6920,
    "event_title": "子どもたちのためのプログラミング初心者/未経験者向け【CoderDojo長門】37回",
    "event_date": "2024-05-25T14:00:00.000+09:00",
    "event_end_at": "2024-05-25T16:00:00.000+09:00",
    "event_url": "https://coderdojonagato.connpass.com/event/314256/",
    "prefecture": "山口",
    "participants": 6,
    "event_update_at": "2024-04-27T17:31:44.000+09:00",
    "address": "山口県長門市仙崎312-1",
    "place": "長門市しごとセンター",
    "limit": 23
  },
  {
    "id": 274,
    "name": "麹町@アドバンスト・ソフト",
    "url": "https://coderdojo-kojimachi.connpass.com/",
    "event_id": 6904,
    "event_title": "第28回 CoderDojo麹町",
    "event_date": "2024-05-19T14:00:00.000+09:00",
    "event_end_at": "2024-05-19T16:00:00.000+09:00",
    "event_url": "https://coderdojo-kojimachi.connpass.com/event/317135/",
    "prefecture": "東京",
    "participants": 11,
    "event_update_at": "2024-04-23T10:16:15.000+09:00",
    "address": "東京都千代田区六番町1-10 山陽六番町ビル4F",
    "place": "株式会社アドバンスト・ソフト",
    "limit": 15
  },
  {
    "id": 278,
    "name": "武蔵小杉",
    "url": "https://coderdojo-musashikosugi.connpass.com/",
    "event_id": 6921,
    "event_title": "第46回 CoderDojo武蔵小杉【レギュラー回】※初めての方歓迎",
    "event_date": "2024-05-11T13:15:00.000+09:00",
    "event_end_at": "2024-05-11T16:00:00.000+09:00",
    "event_url": "https://coderdojo-musashikosugi.connpass.com/event/317686/",
    "prefecture": "神奈川",
    "participants": 2,
    "event_update_at": "2024-04-27T12:50:40.000+09:00",
    "address": "〒211-0004　川崎市中原区新丸子東3-1100-12　1階",
    "place": "かわさき市民活動センター　会議室A/B",
    "limit": 19
  },
  {
    "id": 280,
    "name": "西那須野",
    "url": "https://coder-dojo-nishinasuno.connpass.com/",
    "event_id": 6899,
    "event_title": "第二十七回 CoderDojo西那須野",
    "event_date": "2024-05-19T14:00:00.000+09:00",
    "event_end_at": "2024-05-19T16:00:00.000+09:00",
    "event_url": "https://coder-dojo-nishinasuno.connpass.com/event/315699/",
    "prefecture": "栃木",
    "participants": 3,
    "event_update_at": "2024-04-21T16:01:44.000+09:00",
    "address": "栃木県那須塩原市二区町401",
    "place": "那須塩原市南公民館",
    "limit": 15
  },
  {
    "id": 288,
    "name": "横浜師岡",
    "url": "https://coderdojo-morooka.connpass.com",
    "event_id": 6895,
    "event_title": "CoderDojo横浜師岡（第20回）",
    "event_date": "2024-05-12T09:30:00.000+09:00",
    "event_end_at": "2024-05-12T11:30:00.000+09:00",
    "event_url": "https://coderdojo-morooka.connpass.com/event/316966/",
    "prefecture": "神奈川",
    "participants": 4,
    "event_update_at": "2024-04-20T09:09:29.000+09:00",
    "address": "横浜市港北区師岡町700番地 トレッサ横浜 南棟3F",
    "place": "横浜市師岡コミュニティハウス",
    "limit": 14
  },
  {
    "id": 289,
    "name": "たまち",
    "url": "https://coderdojo-tamachi.connpass.com/",
    "event_id": 6876,
    "event_title": "第18回CoderDojoたまち",
    "event_date": "2024-05-25T14:00:00.000+09:00",
    "event_end_at": "2024-05-25T16:30:00.000+09:00",
    "event_url": "https://coderdojo-tamachi.connpass.com/event/316386/",
    "prefecture": "東京",
    "participants": 1,
    "event_update_at": "2024-04-14T16:48:52.000+09:00",
    "address": "東京都港区芝三丁目41番8号",
    "place": "駐健保会館 中会議室",
    "limit": 12
  },
  {
    "id": 292,
    "name": "二本松",
    "url": "https://coderdojo-nihonmatsu.com/",
    "event_id": 6902,
    "event_title": "子どものためのプログラミング道場「CoderDojo二本松」#17",
    "event_date": "2024-05-12T10:00:00.000+09:00",
    "event_end_at": "2024-05-12T12:00:00.000+09:00",
    "event_url": "https://dojonihonmatsu.doorkeeper.jp/events/172499",
    "prefecture": "福島",
    "participants": 9,
    "event_update_at": "2024-04-23T16:01:42.169+09:00",
    "address": "福島県二本松市油井濡石３",
    "place": "二本松市安達公民館 1階 集会室",
    "limit": 16
  },
  {
    "id": 300,
    "name": "磐田",
    "url": "https://coderdojo-iwata.connpass.com",
    "event_id": 6898,
    "event_title": "第11回 CoderDojo磐田",
    "event_date": "2024-05-25T13:30:00.000+09:00",
    "event_end_at": "2024-05-25T16:30:00.000+09:00",
    "event_url": "https://coderdojo-iwata.connpass.com/event/316441/",
    "prefecture": "静岡",
    "participants": 3,
    "event_update_at": "2024-04-21T16:31:40.000+09:00",
    "address": "〒438-0831 静岡県磐田市上新屋678番地1",
    "place": "磐田市民文化会館 創作活動室1",
    "limit": 13
  },
  {
    "id": 303,
    "name": "鶴岡",
    "url": "https://coderdojo-tsuruoka.connpass.com/",
    "event_id": 6922,
    "event_title": "第11回 CoderDojo Tsuruoka",
    "event_date": "2024-05-25T10:00:00.000+09:00",
    "event_end_at": "2024-05-25T12:00:00.000+09:00",
    "event_url": "https://coderdojo-tsuruoka.connpass.com/event/315188/",
    "prefecture": "山形",
    "participants": 0,
    "event_update_at": "2024-04-27T12:07:42.000+09:00",
    "address": "山形県鶴岡市山王町8-18",
    "place": "古今cocon",
    "limit": 12
  },
  {
    "id": 305,
    "name": "西神",
    "url": "https://twitter.com/CoderDojoSeisin",
    "event_id": 6821,
    "event_title": "第9回 CoderDojo西神",
    "event_date": "2024-05-08T16:00:00.000+09:00",
    "event_end_at": "2024-05-08T22:00:00.000+09:00",
    "event_url": "https://coderdojoseishin.connpass.com/event/315573/",
    "prefecture": "兵庫",
    "participants": 4,
    "event_update_at": "2024-04-05T15:20:52.000+09:00",
    "address": "兵庫県神戸市西区美賀多台1-1-1",
    "place": "西神中央ホール ルーム1",
    "limit": 12
  },
  {
    "id": 307,
    "name": "末広町@アミュレット",
    "url": "https://coderdojosuehirocho.connpass.com/",
    "event_id": 6923,
    "event_title": "CoderDojo末広町 第63回",
    "event_date": "2024-05-25T10:00:00.000+09:00",
    "event_end_at": "2024-05-25T12:00:00.000+09:00",
    "event_url": "https://coderdojosuehirocho.connpass.com/event/317664/",
    "prefecture": "東京",
    "participants": 5,
    "event_update_at": "2024-04-27T12:01:44.000+09:00",
    "address": "東京都千代田区外神田３ー５ー１１",
    "place": "神田キリスト教会　１階ホール",
    "limit": 25
  },
  {
    "id": 308,
    "name": "新代田",
    "url": "https://coder-dojo-shindaita.connpass.com/",
    "event_id": 6754,
    "event_title": "CoderDojo新代田第7回（無料・見学OK）子ども向けプログラミング道場",
    "event_date": "2024-05-18T13:00:00.000+09:00",
    "event_end_at": "2024-05-18T14:00:00.000+09:00",
    "event_url": "https://coder-dojo-shindaita.connpass.com/event/313048/",
    "prefecture": "東京",
    "participants": 4,
    "event_update_at": "2024-04-08T17:46:47.000+09:00",
    "address": "東京都世田谷区代田6丁目21番5号",
    "place": "まもりやまテラス 2階 守山地区会館 図工室",
    "limit": 14
  },
  {
    "id": 312,
    "name": "稲毛海岸",
    "url": "https://coderdojo-inagekaigan.connpass.com/",
    "event_id": 6784,
    "event_title": "CoderDojo稲毛海岸 第６回目",
    "event_date": "2024-05-18T10:00:00.000+09:00",
    "event_end_at": "2024-05-18T12:00:00.000+09:00",
    "event_url": "https://coderdojo-inagekaigan.connpass.com/event/314384/",
    "prefecture": "千葉",
    "participants": 6,
    "event_update_at": "2024-03-25T12:59:58.000+09:00",
    "address": "千葉県千葉市美浜区高洲３丁目１２−１",
    "place": "千葉市 高洲コミュニティセンター",
    "limit": 25
  },
  {
    "id": 316,
    "name": "飯田",
    "url": "https://coderdojoiida.github.io/",
    "event_id": 6712,
    "event_title": "CoderDojo飯田#21",
    "event_date": "2024-05-18T13:30:00.000+09:00",
    "event_end_at": "2024-05-18T15:30:00.000+09:00",
    "event_url": "https://coderdojoiida.connpass.com/event/313118/",
    "prefecture": "長野",
    "participants": 0,
    "event_update_at": "2024-04-03T15:37:56.000+09:00",
    "address": "飯田市上郷別府２６８９−１",
    "place": "ロジカランド株式会社",
    "limit": 15
  }
]