[
  {
    "id": 2,
    "name": "瑞穂",
    "url": "https://coderdojo-mizuho.connpass.com/",
    "event_id": 6185,
    "event_title": "No.114 CoderDojo瑞穂 / Mizuho 現地",
    "event_date": "2023-11-05T09:30:00.000+09:00",
    "event_end_at": "2023-11-05T11:30:00.000+09:00",
    "event_url": "https://coderdojo-mizuho.connpass.com/event/300180/",
    "prefecture": "愛知",
    "participants": 2,
    "event_update_at": "2023-10-23T11:45:06.000+09:00",
    "address": "名古屋市瑞穂区佐渡町３丁目18番地",
    "place": "瑞穂区社会福祉協議会ボランティアセンター",
    "limit": 19
  },
  {
    "id": 13,
    "name": "こだいら",
    "url": "https://coderdojo-kodaira.github.io/",
    "event_id": 6180,
    "event_title": "第303回 あすぴあ会議室（現地）",
    "event_date": "2023-11-05T14:00:00.000+09:00",
    "event_end_at": "2023-11-05T16:30:00.000+09:00",
    "event_url": "https://coderdojo-jp-kodaira.connpass.com/event/300081/",
    "prefecture": "東京",
    "participants": 0,
    "event_update_at": "2023-10-21T07:20:23.000+09:00",
    "address": "小平市小川東町4-2-1 ",
    "place": "小平元気村おがわ東 あすぴあ会議室",
    "limit": 20
  },
  {
    "id": 24,
    "name": "流山",
    "url": "http://www.code-for-nagareyama.org/?cat=11",
    "event_id": 6154,
    "event_title": "CoderDojo流山(2023/11/11(土))@江戸川大学",
    "event_date": "2023-11-11T10:00:00.000+09:00",
    "event_end_at": "2023-11-11T12:00:00.000+09:00",
    "event_url": "https://codefornagareyama.connpass.com/event/299172/",
    "prefecture": "千葉",
    "participants": 1,
    "event_update_at": "2023-10-15T00:01:42.000+09:00",
    "address": "千葉県流山市駒木４７４",
    "place": "江戸川大学 アクティブ・ラーニング・スタジオ(D棟1階112教室)」",
    "limit": 19
  },
  {
    "id": 30,
    "name": "豊橋",
    "url": "https://www.facebook.com/coderdojo.toyohashi/",
    "event_id": 6102,
    "event_title": "CoderDojo豊橋の開校について（2023年10月の開催予定）",
    "event_date": "2023-10-03T16:30:00.000+09:00",
    "event_end_at": "2023-10-31T18:00:00.000+09:00",
    "event_url": "https://coderdojo-toyohashi.doorkeeper.jp/events/164236",
    "prefecture": "愛知",
    "participants": 14,
    "event_update_at": "2023-10-13T07:35:24.382+09:00",
    "address": "〒440-0016 愛知県豊橋市牛川町松下２０−１",
    "place": "豊橋創造大学D22ゼミ室",
    "limit": 17
  },
  {
    "id": 32,
    "name": "天白",
    "url": "https://coderdojo-tempaku.hatenablog.com/",
    "event_id": 6153,
    "event_title": "CoderDojo天白N185",
    "event_date": "2023-11-04T13:30:00.000+09:00",
    "event_end_at": "2023-11-04T16:00:00.000+09:00",
    "event_url": "https://tempaku.connpass.com/event/299474/",
    "prefecture": "愛知",
    "participants": 1,
    "event_update_at": "2023-10-22T17:43:21.000+09:00",
    "address": "〒468-0027 愛知県名古屋市天白区天白町島田黒石4050",
    "place": "天白区生涯学習センター IT室",
    "limit": 8
  },
  {
    "id": 34,
    "name": "長岡京",
    "url": "https://coderdojo-nagaokakyo.doorkeeper.jp/",
    "event_id": 6221,
    "event_title": "CoderDojo長岡京〜学生のためのプログラミング道場〜 89回目",
    "event_date": "2023-11-26T13:30:00.000+09:00",
    "event_end_at": "2023-11-26T16:00:00.000+09:00",
    "event_url": "https://coderdojo-nagaokakyo.doorkeeper.jp/events/165583",
    "prefecture": "京都",
    "participants": 2,
    "event_update_at": "2023-10-29T18:23:49.886+09:00",
    "address": "〒617-0826 京都府長岡京市開田４丁目２−９ ヘルプビル3F",
    "place": "長岡京コワーキングスペース",
    "limit": 8
  },
  {
    "id": 35,
    "name": "奈良",
    "url": "https://coderdojo-nara.github.io/",
    "event_id": 6217,
    "event_title": "【CoderDojo生駒】：子ども向けプログラミング道場（No.76）",
    "event_date": "2023-11-04T13:00:00.000+09:00",
    "event_end_at": "2023-11-04T16:00:00.000+09:00",
    "event_url": "https://coderdojo-nara-ikoma.connpass.com/event/300819/",
    "prefecture": "奈良",
    "participants": 2,
    "event_update_at": "2023-10-29T20:47:38.000+09:00",
    "address": "奈良県生駒市元町1丁目7番6号",
    "place": "市民活動センターららポート",
    "limit": 25
  },
  {
    "id": 44,
    "name": "大阪狭山",
    "url": "https://coderdojo-osakasayama.doorkeeper.jp/",
    "event_id": 6079,
    "event_title": "子ども向けプログラミング道場：コーダー道場 70回目@大阪狭山 with プログラミングでポケモンをうごかしてみよう",
    "event_date": "2023-11-19T09:30:00.000+09:00",
    "event_end_at": "2023-11-19T12:00:00.000+09:00",
    "event_url": "https://coderdojo-osakasayama.doorkeeper.jp/events/164011",
    "prefecture": "大阪",
    "participants": 6,
    "event_update_at": "2023-10-25T09:36:21.877+09:00",
    "address": "大阪狭山市狭山四丁目2303番地の2  (2階)",
    "place": "UPっぷ（子育て支援・世代間交流センター）",
    "limit": 6
  },
  {
    "id": 65,
    "name": "水戸",
    "url": "https://coderdojo-mito.com/",
    "event_id": 6205,
    "event_title": "第８９回 CoderDojo Mito",
    "event_date": "2023-11-26T13:30:00.000+09:00",
    "event_end_at": "2023-11-26T15:30:00.000+09:00",
    "event_url": "https://coderdojo-mito.connpass.com/event/300426/",
    "prefecture": "茨城",
    "participants": 2,
    "event_update_at": "2023-10-25T08:21:30.000+09:00",
    "address": "茨城県水戸市内原町１３９５－６",
    "place": "水戸市内原市民センター",
    "limit": 28
  },
  {
    "id": 71,
    "name": "尾張",
    "url": "https://coderdojoowari.org/",
    "event_id": 6018,
    "event_title": "第80回 CoderDojo Owari",
    "event_date": "2023-11-05T10:00:00.000+09:00",
    "event_end_at": "2023-11-05T12:00:00.000+09:00",
    "event_url": "https://coderdojoowari.connpass.com/event/292521/",
    "prefecture": "愛知",
    "participants": 7,
    "event_update_at": "2023-08-06T20:01:11.000+09:00",
    "address": "愛知県岩倉市本町神明西２０",
    "place": "岩倉市生涯学習センター",
    "limit": null
  },
  {
    "id": 73,
    "name": "ひたちなか",
    "url": "https://www.facebook.com/coderdojo.hitachinaka/",
    "event_id": 6123,
    "event_title": "第68回 CoderDojo Hitachinaka",
    "event_date": "2023-11-03T13:30:00.000+09:00",
    "event_end_at": "2023-11-03T15:30:00.000+09:00",
    "event_url": "https://coderdojo-hitachinaka.connpass.com/event/298744/",
    "prefecture": "茨城",
    "participants": 0,
    "event_update_at": "2023-10-15T01:01:34.000+09:00",
    "address": "ひたちなか市石川町11-1",
    "place": "ふぁみりこらぼ",
    "limit": 9
  },
  {
    "id": 81,
    "name": "岡南",
    "url": "https://www.coderdojo-konan.jp/",
    "event_id": 6131,
    "event_title": "CoderDojo Konan (OKAYAMA) #51",
    "event_date": "2023-11-19T13:30:00.000+09:00",
    "event_end_at": "2023-11-19T16:00:00.000+09:00",
    "event_url": "https://coderdojo-konan.doorkeeper.jp/events/164670",
    "prefecture": "岡山",
    "participants": 1,
    "event_update_at": "2023-10-09T19:38:38.510+09:00",
    "address": "岡山市南区若葉町22-16",
    "place": "岡山市立岡南公民館 大講義室",
    "limit": 10
  },
  {
    "id": 102,
    "name": "福岡",
    "url": "https://www.facebook.com/CoderDojoFukuoka/",
    "event_id": 6168,
    "event_title": "第74回 CoderDojo 福岡 【オンライン】+ 会場：fgn（大名小跡地）",
    "event_date": "2023-11-11T14:00:00.000+09:00",
    "event_end_at": "2023-11-11T16:00:00.000+09:00",
    "event_url": "https://coderdojo-fukuoka.connpass.com/event/299976/",
    "prefecture": "福岡",
    "participants": 9,
    "event_update_at": "2023-10-20T08:43:20.000+09:00",
    "address": "福岡県福岡市中央区大名2-6-11",
    "place": "オンライン + Fukuoka Growth Next",
    "limit": 20
  },
  {
    "id": 105,
    "name": "吉祥寺",
    "url": "https://kichijojijp.wixsite.com/coderdojo",
    "event_id": 6223,
    "event_title": "【現地＋オンライン開催】子どものためのプログラミングクラブ CoderDojo吉祥寺 #66",
    "event_date": "2023-11-05T10:00:00.000+09:00",
    "event_end_at": "2023-11-05T12:00:00.000+09:00",
    "event_url": "https://coderdojo-kichijoji.doorkeeper.jp/events/165584",
    "prefecture": "東京",
    "participants": 2,
    "event_update_at": "2023-10-29T21:28:23.335+09:00",
    "address": "東京都武蔵野市吉祥寺東町3-25-2",
    "place": "本宿コミュニティセンター",
    "limit": null
  },
  {
    "id": 109,
    "name": "滝沢",
    "url": "https://www.facebook.com/CoderDojoTakizawa/",
    "event_id": 6212,
    "event_title": "11/11（土）第61回ＣoderＤojo滝沢 ",
    "event_date": "2023-11-11T09:30:00.000+09:00",
    "event_end_at": "2023-11-11T12:00:00.000+09:00",
    "event_url": "https://coderdojo-takizawa.doorkeeper.jp/events/165512",
    "prefecture": "岩手",
    "participants": 3,
    "event_update_at": "2023-10-28T14:39:47.760+09:00",
    "address": "岩手県滝沢市巣子152-409",
    "place": "滝沢市IPU第二イノベーションセンター",
    "limit": null
  },
  {
    "id": 117,
    "name": "立川",
    "url": "https://coderdojotachikawa.github.io/",
    "event_id": 6134,
    "event_title": "第49回 子どものためのプログラミング道場 - CoderDojo 立川",
    "event_date": "2023-11-11T09:30:00.000+09:00",
    "event_end_at": "2023-11-11T11:30:00.000+09:00",
    "event_url": "https://coderdojo-tachikawa.connpass.com/event/287711/",
    "prefecture": "東京",
    "participants": 0,
    "event_update_at": "2023-10-10T09:01:02.000+09:00",
    "address": "立川市錦町3丁目2番26号",
    "place": "子ども未来センター",
    "limit": 16
  },
  {
    "id": 118,
    "name": "安城",
    "url": "https://sites.google.com/coderdojo.com/anjo/",
    "event_id": 6225,
    "event_title": "【第38回】小中高生のプログラミング道場 CoderDojo Anjo",
    "event_date": "2023-11-18T09:30:00.000+09:00",
    "event_end_at": "2023-11-18T12:00:00.000+09:00",
    "event_url": "https://coderdojo-anjo.doorkeeper.jp/events/165586",
    "prefecture": "愛知",
    "participants": 0,
    "event_update_at": "2023-10-29T21:25:31.699+09:00",
    "address": "愛知県安城市大東町１１−３",
    "place": "安城市民交流センター （1F わくわくセンター）",
    "limit": 10
  },
  {
    "id": 123,
    "name": "池袋",
    "url": "https://coderdojo-ikebukuro.connpass.com/",
    "event_id": 6211,
    "event_title": "第53回 CoderDojo池袋@ユニーク・アイネット",
    "event_date": "2023-11-05T14:00:00.000+09:00",
    "event_end_at": "2023-11-05T16:00:00.000+09:00",
    "event_url": "https://coderdojo-ikebukuro.connpass.com/event/300530/",
    "prefecture": "東京",
    "participants": 3,
    "event_update_at": "2023-10-26T07:19:44.000+09:00",
    "address": "東京都豊島区東池袋1-20-10",
    "place": "としま区民センター",
    "limit": 16
  },
  {
    "id": 126,
    "name": "戸部",
    "url": "https://coderdojo-tobe.connpass.com/",
    "event_id": 6189,
    "event_title": "第65回CoderDojo戸部",
    "event_date": "2023-11-26T13:30:00.000+09:00",
    "event_end_at": "2023-11-26T15:30:00.000+09:00",
    "event_url": "https://coderdojo-tobe.connpass.com/event/300162/",
    "prefecture": "神奈川",
    "participants": 0,
    "event_update_at": "2023-10-22T16:57:31.000+09:00",
    "address": "横浜市西区中央1-5-10",
    "place": "にしとも広場",
    "limit": 6
  },
  {
    "id": 129,
    "name": "三島・沼津",
    "url": "https://coderdojo-mn.com/",
    "event_id": 6124,
    "event_title": "第30回 CoderDojo 三島/沼津",
    "event_date": "2023-11-12T10:00:00.000+09:00",
    "event_end_at": "2023-11-12T12:00:00.000+09:00",
    "event_url": "https://coderdojo-mn.connpass.com/event/298730/",
    "prefecture": "静岡",
    "participants": 2,
    "event_update_at": "2023-10-07T12:01:08.000+09:00",
    "address": "沼津市大岡4044-24",
    "place": "静岡県立工科短期大学校 沼津キャンパス（旧:沼津テクノカレッジ）",
    "limit": 10
  },
  {
    "id": 130,
    "name": "赤羽",
    "url": "https://coderdojo-akabane.com/",
    "event_id": 6201,
    "event_title": "CoderDojo赤羽 #50",
    "event_date": "2023-11-26T09:30:00.000+09:00",
    "event_end_at": "2023-11-26T11:30:00.000+09:00",
    "event_url": "https://coderdojo-akabane.connpass.com/event/300172/",
    "prefecture": "東京",
    "participants": 10,
    "event_update_at": "2023-10-24T08:15:44.000+09:00",
    "address": "東京都北区赤羽西1-6-1-301",
    "place": "赤羽文化センター 第3学習室",
    "limit": 16
  },
  {
    "id": 136,
    "name": "香椎",
    "url": "https://coderdojo-kashii.connpass.com/",
    "event_id": 6176,
    "event_title": "第52回CoderDojo香椎",
    "event_date": "2023-11-12T09:30:00.000+09:00",
    "event_end_at": "2023-11-12T12:00:00.000+09:00",
    "event_url": "https://coderdojo-kashii.connpass.com/event/297990/",
    "prefecture": "福岡",
    "participants": 6,
    "event_update_at": "2023-10-21T10:01:28.000+09:00",
    "address": "福岡市東区千早4丁目21番45号",
    "place": "なみきスクエア　第２多目的室",
    "limit": 10
  },
  {
    "id": 145,
    "name": "日進",
    "url": "https://coderdojo-nisshin.connpass.com/",
    "event_id": 6204,
    "event_title": "CoderDojo日進 子供向けプログラミング道場(会場&オンライン)2023/11/12",
    "event_date": "2023-11-12T09:00:00.000+09:00",
    "event_end_at": "2023-11-12T11:00:00.000+09:00",
    "event_url": "https://coderdojo-nisshin.connpass.com/event/300447/",
    "prefecture": "愛知",
    "participants": 2,
    "event_update_at": "2023-10-25T12:14:01.000+09:00",
    "address": "愛知県日進市蟹甲町中島277-1",
    "place": "にぎわい交流館",
    "limit": null
  },
  {
    "id": 147,
    "name": "稲城",
    "url": "https://coderdojo-inagi.doorkeeper.jp/",
    "event_id": 6091,
    "event_title": "【オンライン＆オフライン開催】子ども向けプログラミング道場：CoderDojo稲城71回",
    "event_date": "2023-11-26T13:00:00.000+09:00",
    "event_end_at": "2023-11-26T15:00:00.000+09:00",
    "event_url": "https://coderdojo-inagi.doorkeeper.jp/events/162509",
    "prefecture": "東京",
    "participants": 3,
    "event_update_at": "2023-10-28T22:24:40.764+09:00",
    "address": null,
    "place": null,
    "limit": 20
  },
  {
    "id": 149,
    "name": "白河",
    "url": "https://coderdojoshirakawa.hateblo.jp/entry/top",
    "event_id": 6196,
    "event_title": "第56回 CoderDojo白河",
    "event_date": "2023-12-09T09:30:00.000+09:00",
    "event_end_at": "2023-12-09T11:30:00.000+09:00",
    "event_url": "https://coderdojo-shirakawa.doorkeeper.jp/events/165069",
    "prefecture": "福島",
    "participants": 2,
    "event_update_at": "2023-10-29T18:21:24.441+09:00",
    "address": "〒961-0905 福島県白河市本町２",
    "place": "マイタウン白河 2F 中会議室1",
    "limit": 11
  },
  {
    "id": 153,
    "name": "多摩センター",
    "url": "https://coderdojo-tamacent.wixsite.com/main",
    "event_id": 6222,
    "event_title": "子どものためのプログラミング道場　第60回 CoderDojo多摩センター (11月度)",
    "event_date": "2023-11-26T10:00:00.000+09:00",
    "event_end_at": "2023-11-26T11:30:00.000+09:00",
    "event_url": "https://coderdojo-tamacenter.doorkeeper.jp/events/165578",
    "prefecture": "東京",
    "participants": 1,
    "event_update_at": "2023-10-29T13:06:02.004+09:00",
    "address": "東京都多摩市鶴牧6丁目14番地",
    "place": "唐木田しょうぶ館 会議室３",
    "limit": 7
  },
  {
    "id": 156,
    "name": "古河",
    "url": "https://coderdojokoga.connpass.com/",
    "event_id": 6121,
    "event_title": "第72回CoderDojo Koga（コーダー道場 古河）",
    "event_date": "2023-11-11T10:00:00.000+09:00",
    "event_end_at": "2023-11-11T12:00:00.000+09:00",
    "event_url": "https://coderdojokoga.connpass.com/event/298779/",
    "prefecture": "茨城",
    "participants": 5,
    "event_update_at": "2023-10-07T23:01:08.000+09:00",
    "address": "茨城県古河市鴻巣７５８",
    "place": "三桜工業株式会社　古河事業所",
    "limit": 14
  },
  {
    "id": 165,
    "name": "喜多方",
    "url": "https://www.coderdojo-kitakata.com/",
    "event_id": 6195,
    "event_title": "第53回 CoderDojo喜多方 in M!KKE（プロコン表彰式もあるよ）",
    "event_date": "2023-11-11T10:00:00.000+09:00",
    "event_end_at": "2023-11-11T12:00:00.000+09:00",
    "event_url": "https://coderdojo-kitakata.doorkeeper.jp/events/165311",
    "prefecture": "福島",
    "participants": 2,
    "event_update_at": "2023-10-25T12:26:13.701+09:00",
    "address": " 福島県喜多方市西四ツ谷295",
    "place": "M!KKE 3Fレンタルスペース ",
    "limit": 10
  },
  {
    "id": 182,
    "name": "瀬戸",
    "url": "https://coderdojo-seto.jp/",
    "event_id": 6166,
    "event_title": "【無料】【小会議室（ぐるっぺ）】CoderDojo瀬戸(第113回) 子供プログラミングコミュニティ",
    "event_date": "2023-11-05T10:00:00.000+09:00",
    "event_end_at": "2023-11-05T12:00:00.000+09:00",
    "event_url": "https://coderdojo-seto.connpass.com/event/299859/",
    "prefecture": "愛知",
    "participants": 12,
    "event_update_at": "2023-10-18T19:55:55.000+09:00",
    "address": "愛知県瀬戸市道泉町53番地の5",
    "place": "ぐるっぺ道泉",
    "limit": null
  },
  {
    "id": 184,
    "name": "あざみ野",
    "url": "https://coderdojo-azamino.connpass.com/",
    "event_id": 6111,
    "event_title": "第60回CoderDojoあざみ野(横浜青葉)",
    "event_date": "2023-11-18T14:00:00.000+09:00",
    "event_end_at": "2023-11-18T16:00:00.000+09:00",
    "event_url": "https://coderdojo-azamino.connpass.com/event/298057/",
    "prefecture": "神奈川",
    "participants": 5,
    "event_update_at": "2023-10-01T11:47:09.000+09:00",
    "address": "横浜市青葉区あざみ野南1-17-3",
    "place": "アートフォーラムあざみ野 2F セミナールーム2",
    "limit": 7
  },
  {
    "id": 186,
    "name": "名護",
    "url": "https://coderdojo-nago.connpass.com/",
    "event_id": 6142,
    "event_title": "CoderDojo名護（屋部地区センター・会議室）",
    "event_date": "2023-11-05T10:30:00.000+09:00",
    "event_end_at": "2023-11-05T12:00:00.000+09:00",
    "event_url": "https://coderdojo-nago.connpass.com/event/299261/",
    "prefecture": "沖縄",
    "participants": 5,
    "event_update_at": "2023-10-24T12:26:48.000+09:00",
    "address": "沖縄県名護市屋部４４",
    "place": "屋部地区センター・会議室",
    "limit": null
  },
  {
    "id": 189,
    "name": "まちだ",
    "url": "https://coderdojo-machida.connpass.com/",
    "event_id": 6051,
    "event_title": "CoderDojoまちだ　第５２回",
    "event_date": "2023-11-03T13:30:00.000+09:00",
    "event_end_at": "2023-11-03T16:30:00.000+09:00",
    "event_url": "https://coderdojo-machida.connpass.com/event/296679/",
    "prefecture": "東京",
    "participants": 7,
    "event_update_at": "2023-10-15T13:29:27.000+09:00",
    "address": "東京都町田市原町田４丁目９−８ サウスフロントタワー町田内",
    "place": "町田市民フォーラム",
    "limit": null
  },
  {
    "id": 190,
    "name": "溝口",
    "url": "https://coderdojo-mizonokuchi.connpass.com/",
    "event_id": 6173,
    "event_title": "11/19無料の子どもプログラミングサークル【第48回CoderDojo溝口】(オンライン)",
    "event_date": "2023-11-19T13:00:00.000+09:00",
    "event_end_at": "2023-11-19T14:00:00.000+09:00",
    "event_url": "https://coderdojo-mizonokuchi.connpass.com/event/298731/",
    "prefecture": "神奈川",
    "participants": 0,
    "event_update_at": "2023-10-21T12:01:16.000+09:00",
    "address": "オンライン",
    "place": "オンライン",
    "limit": 11
  },
  {
    "id": 193,
    "name": "とよなか",
    "url": "https://coderdojo-toyonaka.connpass.com/",
    "event_id": 6062,
    "event_title": "第57回 CoderDojoとよなか（大阪）2023/11/18(土)",
    "event_date": "2023-11-18T09:00:00.000+09:00",
    "event_end_at": "2023-11-18T12:00:00.000+09:00",
    "event_url": "https://coderdojo-toyonaka.connpass.com/event/295129/",
    "prefecture": "大阪",
    "participants": 0,
    "event_update_at": "2023-08-31T22:01:30.000+09:00",
    "address": "豊中市蛍池中町3-2-1-501",
    "place": "豊中市蛍池公民館第１講座室",
    "limit": 22
  },
  {
    "id": 206,
    "name": "吹田",
    "url": "https://coderdojo-suita.doorkeeper.jp/",
    "event_id": 6120,
    "event_title": "子ども向けプログラミング道場：CoderDojo吹田 #31",
    "event_date": "2023-11-25T13:30:00.000+09:00",
    "event_end_at": "2023-11-25T16:00:00.000+09:00",
    "event_url": "https://coderdojo-suita.doorkeeper.jp/events/164599",
    "prefecture": "大阪",
    "participants": 3,
    "event_update_at": "2023-10-21T16:01:26.401+09:00",
    "address": "大阪府吹田市南吹田２丁目１６−６−３",
    "place": "株式会社6VOX",
    "limit": null
  },
  {
    "id": 210,
    "name": "久地",
    "url": "https://www.facebook.com/coderdojokuji/",
    "event_id": 6203,
    "event_title": "【無料】第52回 CoderDojoKuji(コーダー道場久地)",
    "event_date": "2023-11-11T14:15:00.000+09:00",
    "event_end_at": "2023-11-11T16:30:00.000+09:00",
    "event_url": "https://coderdojo-kuji.connpass.com/event/300490/",
    "prefecture": "神奈川",
    "participants": 0,
    "event_update_at": "2023-10-25T18:46:24.000+09:00",
    "address": "〒213-0032 神奈川県川崎市高津区久地３丁目１６−５",
    "place": "溝の口ガーデンアクアス　B棟１階パーティラウンジ",
    "limit": 20
  },
  {
    "id": 216,
    "name": "那覇",
    "url": "https://coderdojo-naha.doorkeeper.jp/",
    "event_id": 6209,
    "event_title": "第38回 CoderDojo 那覇 (現地開催)",
    "event_date": "2023-11-04T10:00:00.000+09:00",
    "event_end_at": "2023-11-04T12:00:00.000+09:00",
    "event_url": "https://coderdojo-naha.doorkeeper.jp/events/165440",
    "prefecture": "沖縄",
    "participants": 4,
    "event_update_at": "2023-10-29T21:51:34.619+09:00",
    "address": "〒900-0004 沖縄県那覇市銘苅2-3-6",
    "place": "那覇市IT創造館、IT研修室",
    "limit": 4
  },
  {
    "id": 218,
    "name": "犬山",
    "url": "https://coderdojo-inuyama.rgr.jp/",
    "event_id": 6162,
    "event_title": "第53回 CoderDojo犬山　（午後）",
    "event_date": "2023-11-19T13:30:00.000+09:00",
    "event_end_at": "2023-11-19T15:30:00.000+09:00",
    "event_url": "https://coderdojo-inuyama.doorkeeper.jp/events/164990",
    "prefecture": "愛知",
    "participants": 1,
    "event_update_at": "2023-10-19T07:25:47.511+09:00",
    "address": "〒484-0081 犬山市大字犬山字中ノ宮43-1",
    "place": "犬山市 丸山地区学習等供用施設",
    "limit": null
  },
  {
    "id": 227,
    "name": "戸田公園",
    "url": "https://coderdojo-todakoen.com/",
    "event_id": 6214,
    "event_title": "第40回 CoderDojo 戸田公園",
    "event_date": "2023-11-04T10:00:00.000+09:00",
    "event_end_at": "2023-11-04T12:00:00.000+09:00",
    "event_url": "https://corderdojo-todakoen.connpass.com/event/300735/",
    "prefecture": "埼玉",
    "participants": 5,
    "event_update_at": "2023-10-28T11:19:20.000+09:00",
    "address": "埼玉県戸田市本町1-3-3(ライオンズマンション戸田公園206)",
    "place": "(有)ミネルバ内 会議室",
    "limit": 5
  },
  {
    "id": 239,
    "name": "松山",
    "url": "https://coderdojo-matsuyama.doorkeeper.jp/",
    "event_id": 6183,
    "event_title": "自由にプログラミングを学ぶ場 CoderDojo松山#95",
    "event_date": "2023-11-03T13:00:00.000+09:00",
    "event_end_at": "2023-11-03T17:00:00.000+09:00",
    "event_url": "https://coderdojo-matsuyama.doorkeeper.jp/events/165303",
    "prefecture": "愛媛",
    "participants": 0,
    "event_update_at": "2023-10-21T15:47:29.764+09:00",
    "address": "〒790-0012  愛媛県松山市湊町4丁目10−6 BLESSビル3F",
    "place": "コドモノイバショ",
    "limit": 8
  },
  {
    "id": 240,
    "name": "京都四条",
    "url": "https://coderdojo-kyoto-shijo.doorkeeper.jp/",
    "event_id": 6213,
    "event_title": "子ども向けプログラミング道場：コーダー道場2回目@京都四条",
    "event_date": "2023-11-12T13:00:00.000+09:00",
    "event_end_at": "2023-11-12T16:00:00.000+09:00",
    "event_url": "https://coderdojo-kyoto-shijo.doorkeeper.jp/events/165515",
    "prefecture": "京都",
    "participants": 0,
    "event_update_at": "2023-10-27T09:23:41.878+09:00",
    "address": "京都府京都市下京区立売東町12-1 日土地京都四条通ビル 8F",
    "place": "ポノス株式会社",
    "limit": 13
  },
  {
    "id": 241,
    "name": "西尾",
    "url": "https://www.coderdojo-nishio.com/",
    "event_id": 6125,
    "event_title": "11月度 CoderDojo Nishio(こーだーどうじょうにしお）",
    "event_date": "2023-11-11T10:00:00.000+09:00",
    "event_end_at": "2023-11-11T11:30:00.000+09:00",
    "event_url": "https://coderdojo-nishio.doorkeeper.jp/events/164651",
    "prefecture": "愛知",
    "participants": 0,
    "event_update_at": "2023-10-07T10:30:25.652+09:00",
    "address": "愛知県西尾市鶴ケ崎町６−２",
    "place": "アクティ西尾　3F  3B",
    "limit": 13
  },
  {
    "id": 243,
    "name": "大府",
    "url": "https://coderdojo-obu.connpass.com/",
    "event_id": 6127,
    "event_title": "CoderDojo大府(第70回) 子供向けプログラミング道場 2023/11/12",
    "event_date": "2023-11-12T09:30:00.000+09:00",
    "event_end_at": "2023-11-12T11:30:00.000+09:00",
    "event_url": "https://coderdojo-obu.connpass.com/event/298827/",
    "prefecture": "愛知",
    "participants": 4,
    "event_update_at": "2023-10-08T22:06:27.000+09:00",
    "address": "〒474-0053 愛知県大府市柊山町６丁目１５０−１",
    "place": "おおぶ文化交流の杜 allobu",
    "limit": 17
  },
  {
    "id": 248,
    "name": "矢吹",
    "url": "https://coderdojoyabuki.connpass.com/",
    "event_id": 6149,
    "event_title": "出張CoderDojo Yabuki in Koriyama vol.2",
    "event_date": "2023-11-03T10:00:00.000+09:00",
    "event_end_at": "2023-11-03T12:00:00.000+09:00",
    "event_url": "https://coderdojoyabuki.connpass.com/event/299438/",
    "prefecture": "福島",
    "participants": 0,
    "event_update_at": "2023-10-14T15:19:59.000+09:00",
    "address": null,
    "place": null,
    "limit": 5
  },
  {
    "id": 249,
    "name": "加西",
    "url": "https://coderdojokasai.connpass.com/",
    "event_id": 6129,
    "event_title": "第40回 CoderDojo加西",
    "event_date": "2023-11-12T10:15:00.000+09:00",
    "event_end_at": "2023-11-12T12:00:00.000+09:00",
    "event_url": "https://coderdojokasai.connpass.com/event/298788/",
    "prefecture": "兵庫",
    "participants": 0,
    "event_update_at": "2023-10-08T08:23:43.000+09:00",
    "address": "兵庫県加西市北条町北条28-1",
    "place": "加西市立図書館",
    "limit": 6
  },
  {
    "id": 254,
    "name": "青梅",
    "url": "https://coderdojoome.github.io/",
    "event_id": 6137,
    "event_title": "子供たちのためのプログラミング初心者/未経験者向け【CoderDojo青梅】",
    "event_date": "2023-11-26T09:45:00.000+09:00",
    "event_end_at": "2023-11-26T12:00:00.000+09:00",
    "event_url": "https://coderdojo-ome.connpass.com/event/298777/",
    "prefecture": "東京",
    "participants": 21,
    "event_update_at": "2023-10-14T22:04:29.000+09:00",
    "address": "東京都青梅市東青梅１丁目１７７−３ 青梅市福祉センター",
    "place": "青梅市福祉センター第１・２集会室",
    "limit": 28
  },
  {
    "id": 260,
    "name": "伊勢原",
    "url": "https://coderdojo-isehara.connpass.com",
    "event_id": 6147,
    "event_title": "第31回　CoderDojo伊勢原",
    "event_date": "2023-11-11T14:00:00.000+09:00",
    "event_end_at": "2023-11-11T16:00:00.000+09:00",
    "event_url": "https://coderdojo-isehara.connpass.com/event/298201/",
    "prefecture": "神奈川",
    "participants": 1,
    "event_update_at": "2023-10-13T07:01:44.000+09:00",
    "address": "伊勢原市田中２９７番地",
    "place": "伊勢原市民活動サポートセンター",
    "limit": 10
  },
  {
    "id": 261,
    "name": "江別",
    "url": "https://coderdojo-ebetsu.connpass.com/",
    "event_id": 6188,
    "event_title": "第２３回 CoderDojo江別",
    "event_date": "2023-11-04T14:00:00.000+09:00",
    "event_end_at": "2023-11-04T16:00:00.000+09:00",
    "event_url": "https://coderdojo-ebetsu.connpass.com/event/300173/",
    "prefecture": "北海道",
    "participants": 0,
    "event_update_at": "2023-10-23T21:10:24.000+09:00",
    "address": "北海道江別市東野幌本町6-43",
    "place": "市民交流施設 ぷらっと",
    "limit": null
  },
  {
    "id": 264,
    "name": "藤井寺",
    "url": "https://www.coderdojo-fujiidera-kashiwara.com",
    "event_id": 6208,
    "event_title": "やってみよう！プログラミング ! 第22回 CoderDojo藤井寺",
    "event_date": "2023-11-26T09:30:00.000+09:00",
    "event_end_at": "2023-11-26T12:00:00.000+09:00",
    "event_url": "https://coderdojo-fujiidera.doorkeeper.jp/events/165509",
    "prefecture": "大阪",
    "participants": 0,
    "event_update_at": "2023-10-25T22:05:46.041+09:00",
    "address": "大阪府藤井寺市国府1丁目1-7 里庭の箱",
    "place": "ノーウェア土師ノ里",
    "limit": 5
  },
  {
    "id": 265,
    "name": "八戸@吹上",
    "url": "https://coderdojo-hachinohe.aomori.jp/",
    "event_id": 6181,
    "event_title": "やってみよう！プログラミング ! 第25回 CoderDojo八戸@鮫のゲストハウスDrop in",
    "event_date": "2023-11-19T10:00:00.000+09:00",
    "event_end_at": "2023-11-19T12:00:00.000+09:00",
    "event_url": "https://coderdojo-hachinohe.doorkeeper.jp/events/165300",
    "prefecture": "青森",
    "participants": 0,
    "event_update_at": "2023-10-21T15:47:13.546+09:00",
    "address": "青森県八戸市蟻子5-11",
    "place": "鮫のゲストハウス Drop in",
    "limit": 4
  },
  {
    "id": 270,
    "name": "長門",
    "url": "https://sites.google.com/view/coderdojonagato",
    "event_id": 6138,
    "event_title": "第17回　非エンジニアだけど学んでみたいpythonもくもく会",
    "event_date": "2023-11-08T18:15:00.000+09:00",
    "event_end_at": "2023-11-08T19:30:00.000+09:00",
    "event_url": "https://coderdojonagato.connpass.com/event/296699/",
    "prefecture": "山口",
    "participants": 1,
    "event_update_at": "2023-10-12T10:44:15.000+09:00",
    "address": "山口県長門市仙崎312-1",
    "place": "長門市しごとセンター",
    "limit": 9
  },
  {
    "id": 274,
    "name": "麹町@アドバンスト・ソフト",
    "url": "https://coderdojo-kojimachi.connpass.com/",
    "event_id": 6198,
    "event_title": "第23回 CoderDojo麹町",
    "event_date": "2023-11-19T14:00:00.000+09:00",
    "event_end_at": "2023-11-19T16:00:00.000+09:00",
    "event_url": "https://coderdojo-kojimachi.connpass.com/event/300234/",
    "prefecture": "東京",
    "participants": 8,
    "event_update_at": "2023-10-23T13:35:59.000+09:00",
    "address": "東京都千代田区六番町1-10 山陽六番町ビル4F",
    "place": "株式会社アドバンスト・ソフト",
    "limit": 11
  },
  {
    "id": 278,
    "name": "武蔵小杉",
    "url": "https://coderdojo-musashikosugi.connpass.com/",
    "event_id": 6218,
    "event_title": "第38回 CoderDojo武蔵小杉【レギュラー回】※初めての方歓迎",
    "event_date": "2023-11-25T13:15:00.000+09:00",
    "event_end_at": "2023-11-25T16:00:00.000+09:00",
    "event_url": "https://coderdojo-musashikosugi.connpass.com/event/300791/",
    "prefecture": "神奈川",
    "participants": 2,
    "event_update_at": "2023-10-29T13:30:32.000+09:00",
    "address": "〒211-0004　川崎市中原区新丸子東3-1100-12　1階",
    "place": "かわさき市民活動センター　会議室A/B",
    "limit": 19
  },
  {
    "id": 280,
    "name": "西那須野",
    "url": "https://coder-dojo-nishinasuno.connpass.com/",
    "event_id": 6136,
    "event_title": "出張版CoderDojo西那須野 in なしお博2023",
    "event_date": "2023-11-11T08:30:00.000+09:00",
    "event_end_at": "2023-11-11T16:00:00.000+09:00",
    "event_url": "https://coder-dojo-nishinasuno.connpass.com/event/299153/",
    "prefecture": "栃木",
    "participants": 1,
    "event_update_at": "2023-10-17T22:52:07.000+09:00",
    "address": "栃木県那須塩原市鹿野崎131",
    "place": "宇都宮共和大学那須キャンパス",
    "limit": 10
  },
  {
    "id": 286,
    "name": "池田石橋",
    "url": "https://coderdojo-ikeda.connpass.com/",
    "event_id": 6169,
    "event_title": "CoderDojo 池田石橋@正福寺 - 14",
    "event_date": "2023-11-05T09:30:00.000+09:00",
    "event_end_at": "2023-11-05T12:30:00.000+09:00",
    "event_url": "https://coderdojo-ikeda.connpass.com/event/300119/",
    "prefecture": "大阪",
    "participants": 2,
    "event_update_at": "2023-10-21T19:40:46.000+09:00",
    "address": "大阪府池田市石橋４ー１５ー１４",
    "place": "ナムのひろば文化会館",
    "limit": 10
  },
  {
    "id": 288,
    "name": "横浜師岡",
    "url": "https://coderdojo-morooka.connpass.com",
    "event_id": 6172,
    "event_title": "CoderDojo横浜師岡（第14回）",
    "event_date": "2023-11-23T09:30:00.000+09:00",
    "event_end_at": "2023-11-23T11:30:00.000+09:00",
    "event_url": "https://coderdojo-morooka.connpass.com/event/300108/",
    "prefecture": "神奈川",
    "participants": 3,
    "event_update_at": "2023-10-21T14:32:15.000+09:00",
    "address": "横浜市港北区師岡町700番地 トレッサ横浜 南棟3F",
    "place": "横浜市師岡コミュニティハウス",
    "limit": 14
  },
  {
    "id": 289,
    "name": "たまち",
    "url": "https://coderdojo-tamachi.connpass.com/",
    "event_id": 6171,
    "event_title": "第12回CoderDojoたまち",
    "event_date": "2023-11-19T14:00:00.000+09:00",
    "event_end_at": "2023-11-19T16:30:00.000+09:00",
    "event_url": "https://coderdojo-tamachi.connpass.com/event/300106/",
    "prefecture": "東京",
    "participants": 1,
    "event_update_at": "2023-10-21T16:32:56.000+09:00",
    "address": "東京都港区芝三丁目41番8号",
    "place": "駐健保会館 中会議室",
    "limit": 12
  },
  {
    "id": 300,
    "name": "磐田",
    "url": "https://coderdojo-iwata.connpass.com",
    "event_id": 6043,
    "event_title": "第5回 CoderDojo磐田",
    "event_date": "2023-11-12T13:30:00.000+09:00",
    "event_end_at": "2023-11-12T16:45:00.000+09:00",
    "event_url": "https://coderdojo-iwata.connpass.com/event/296167/",
    "prefecture": "静岡",
    "participants": 0,
    "event_update_at": "2023-09-10T22:07:40.000+09:00",
    "address": "静岡県磐田市見付2989-3",
    "place": "ワークピア磐田 視聴覚室",
    "limit": 12
  },
  {
    "id": 301,
    "name": "岩国",
    "url": "https://coderdojo-iwakuni.connpass.com/",
    "event_id": 6216,
    "event_title": "CodeDojo 岩国 6回目（子供たちのプログラミングクラブ活動）",
    "event_date": "2023-11-25T14:00:00.000+09:00",
    "event_end_at": "2023-11-25T16:00:00.000+09:00",
    "event_url": "https://coderdojo-iwakuni.connpass.com/event/300825/",
    "prefecture": "山口",
    "participants": 0,
    "event_update_at": "2023-10-29T21:38:34.000+09:00",
    "address": "山口県岩国市周東町下久原1208-1",
    "place": "周東中央公民館（総合センター日向）2階第2講座室",
    "limit": 20
  },
  {
    "id": 305,
    "name": "西神",
    "url": "https://twitter.com/CoderDojoSeisin",
    "event_id": 6175,
    "event_title": "第3回 CoderDojo西神",
    "event_date": "2023-11-01T18:00:00.000+09:00",
    "event_end_at": "2023-11-01T22:00:00.000+09:00",
    "event_url": "https://coderdojoseishin.connpass.com/event/297045/",
    "prefecture": "兵庫",
    "participants": 1,
    "event_update_at": "2023-10-24T23:37:11.000+09:00",
    "address": "兵庫県神戸市西区美賀多台1-1-1",
    "place": "西神中央ホール ルーム1",
    "limit": 8
  },
  {
    "id": 306,
    "name": "足利",
    "url": "https://coderdojo-ashikaga.com/",
    "event_id": 6202,
    "event_title": "CoderDojo足利 第4回（11/19、マチノテ）",
    "event_date": "2023-11-19T10:00:00.000+09:00",
    "event_end_at": "2023-11-19T12:00:00.000+09:00",
    "event_url": "https://coderdojo-ashikaga.connpass.com/event/300525/",
    "prefecture": "栃木",
    "participants": 0,
    "event_update_at": "2023-10-26T02:54:55.000+09:00",
    "address": "足利市伊勢町3-4-8",
    "place": "マチノテ",
    "limit": 16
  },
  {
    "id": 307,
    "name": "末広町@アミュレット",
    "url": "https://coderdojosuehirocho.connpass.com/",
    "event_id": 6174,
    "event_title": "CoderDojo末広町 第57回",
    "event_date": "2023-11-25T10:00:00.000+09:00",
    "event_end_at": "2023-11-25T12:00:00.000+09:00",
    "event_url": "https://coderdojosuehirocho.connpass.com/event/300076/",
    "prefecture": "東京",
    "participants": 3,
    "event_update_at": "2023-10-21T12:01:16.000+09:00",
    "address": "東京都千代田区外神田３ー５ー１１",
    "place": "神田キリスト教会　１階ホール",
    "limit": 25
  },
  {
    "id": 308,
    "name": "新代田",
    "url": "https://coderdojoshindaita.peatix.com/",
    "event_id": 6055,
    "event_title": "CoderDojo新代田 #02",
    "event_date": "2023-11-04T13:00:00.000+09:00",
    "event_end_at": "2023-11-04T14:00:00.000+09:00",
    "event_url": "https://coder-dojo-shindaita.connpass.com/event/296718/",
    "prefecture": "東京",
    "participants": 1,
    "event_update_at": "2023-09-16T17:04:38.000+09:00",
    "address": "東京都世田谷区代田6丁目34番13号",
    "place": "代田区民センター　地下2階　第4会議室",
    "limit": 8
  }
]